sid_summation_module/__init__.py
sid_summation_module/sid_summation_module.py
sid_summation_module-0.1.dist-info/LICENSE.txt
sid_summation_module-0.1.dist-info/METADATA
sid_summation_module-0.1.dist-info/WHEEL
sid_summation_module-0.1.dist-info/top_level.txt
sid_summation_module-0.1.dist-info/RECORD
