Metadata-Version: 2.1
Name: sid-summation-module
Version: 0.1
Summary: module for summation of two numbers
Home-page: UNKNOWN
Author: siddharth garg
Author-email: sidd.garg786@gmail.com
License: UNKNOWN
Platform: UNKNOWN
Classifier: Programming Language :: Python :: 3
Classifier: License :: OSI Approved :: MIT License
Classifier: Operating System :: OS Independent
